fastsnake/__init__.py
fastsnake/__main__.py
fastsnake/entries.py
fastsnake/algorithms/binary_search.py
fastsnake/algorithms/extended_gcd.py
fastsnake/algorithms/gcd.py
fastsnake/algorithms/knapsack.py
fastsnake/algorithms/largest_sub_array_sum.py
fastsnake/algorithms/lcm.py
fastsnake/algorithms/longest_common_subsequence.py
fastsnake/algorithms/longest_increasing_subsequence.py
fastsnake/algorithms/lower_bound.py
fastsnake/algorithms/mex.py
fastsnake/algorithms/min_coins.py
fastsnake/algorithms/upper_bound.py
fastsnake/application/application.py
fastsnake/application/arg_parser.py
fastsnake/application/config.py
fastsnake/application/contest.py
fastsnake/application/external.py
fastsnake/application/runner.py
fastsnake/application/runner_tools.py
fastsnake/external/__init__.py
fastsnake/structures/b_tree.py
fastsnake/templates/solution.cpp
fastsnake/templates/solution.py
fastsnake/templates/test_generator.py
fastsnake/util/atcoder.py
fastsnake/util/codeforces.py
fastsnake/util/compiler.py
fastsnake/util/step_counter.py
fastsnake-1.5.7.dist-info/METADATA
fastsnake-1.5.7.dist-info/WHEEL
fastsnake-1.5.7.dist-info/entry_points.txt
fastsnake-1.5.7.dist-info/licenses/LICENSE
fastsnake-1.5.7.dist-info/RECORD
