Metadata-Version: 2.3
Name: FastSnake
Version: 1.5.7
Summary: A Python Helper CLI for Competitive Programming
Project-URL: Homepage, https://github.com/JeanExtreme002/FastSnake
Author-email: Jean Loui Bernard Silva de Jesus <jeanextreme002@gmail.com>
License-Expression: MIT
License-File: LICENSE
Keywords: algorithms,cli,codeforces,competition,competitive programming,contest,helper,marathon,structures
Classifier: Intended Audience :: Developers
Classifier: License :: OSI Approved :: MIT License
Requires-Python: >=3.6
Requires-Dist: beautifulsoup4
Requires-Dist: requests
Provides-Extra: tests
Requires-Dist: pytest; extra == 'tests'
